coins_parser/CITATION.cff
coins_parser/__init__.py
coins_parser/main.py
coins_parser-2.0.0.dist-info/METADATA
coins_parser-2.0.0.dist-info/WHEEL
coins_parser-2.0.0.dist-info/licenses/LICENSE
coins_parser-2.0.0.dist-info/RECORD
