Metadata-Version: 2.4
Name: coins-parser
Version: 2.0.0
Summary: Parses and creates COinS metadata tags. Can be used with Zotero.
Project-URL: Homepage, https://github.com/willynilly/coins-parser
Project-URL: Documentation, https://github.com/willynilly/coins-parser#readme
Project-URL: Issues, https://github.com/willynilly/coins-parser/issues
Project-URL: Source, https://github.com/willynilly/coins-parser
Author-email: Will Riley <wanderingwill@gmail.com>
License-Expression: Apache-2.0
License-File: LICENSE
Keywords: COinS,Zotero,citation,metadata,parser
Classifier: Development Status :: 3 - Alpha
Classifier: Intended Audience :: Developers
Classifier: Intended Audience :: Education
Classifier: Intended Audience :: Information Technology
Classifier: Intended Audience :: Science/Research
Classifier: Intended Audience :: System Administrators
Classifier: License :: OSI Approved :: Apache Software License
Classifier: Natural Language :: English
Classifier: Programming Language :: Python
Classifier: Programming Language :: Python :: 3
Classifier: Programming Language :: Python :: 3.9
Classifier: Topic :: Scientific/Engineering
Classifier: Topic :: Software Development
Classifier: Topic :: Utilities
Requires-Python: >=3.9
Requires-Dist: beautifulsoup4>=4.13.4
Provides-Extra: testing
Requires-Dist: pytest>=8.1.1; extra == 'testing'
